enotype/__init__.py
enotype/de.py
enotype/en.py
enotype/es.py
enotype-0.3.0.dist-info/LICENSE.txt
enotype-0.3.0.dist-info/METADATA
enotype-0.3.0.dist-info/WHEEL
enotype-0.3.0.dist-info/top_level.txt
enotype-0.3.0.dist-info/RECORD
