Metadata-Version: 2.1
Name: enotype
Version: 0.3.0
Summary: A cross-language type library
Home-page: https://eno-lang.org/enotype/
Author: Simon Repp
Author-email: simon@fdpl.io
License: MIT
Platform: UNKNOWN
Classifier: Programming Language :: Python :: 3
Classifier: Programming Language :: Python :: 3.6
Classifier: License :: OSI Approved :: MIT License
Classifier: Operating System :: OS Independent
